{
	"name": "5_json",
	"properties": {
		"folder": {
			"name": "nyc_taxi/discovery"
		},
		"content": {
			"query": "--Desplay json values as json\n\nSELECT *\nFROM OPENROWSET(\n    BULK 'payment_type.json',\n    DATA_SOURCE = 'nyc_taxi_data_raw',\n    FORMAT = 'CSV',\n    PARSER_VERSION = '1.0',\n    FIELDTERMINATOR ='0x0b',\n    FIELDQUOTE='0x0b',\n    ROWTERMINATOR = '0x0b'\n ) \n WITH (\n    jsonDoc NVARCHAR(MAX)\n ) AS payment_type\n\n--display json in column format\n\nSELECT JSON_VALUE(jsonDoc,'$.payment_type') payment_type,\n       JSON_VALUE(jsonDoc,'$.payment_type_desc') payment_type_desc  \nFROM OPENROWSET(\n    BULK 'payment_type.json',\n    DATA_SOURCE = 'nyc_taxi_data_raw',\n    FORMAT = 'CSV',\n    PARSER_VERSION = '1.0',\n    FIELDTERMINATOR ='0x0b',\n    FIELDQUOTE='0x0b',\n    ROWTERMINATOR = '0x0a'\n ) \n WITH (\n    jsonDoc NVARCHAR(MAX)\n ) AS payment_type\n\n\n--here if we run this the value is nvarchar(4000)\nEXEC sp_describe_first_result_set N'\nSELECT JSON_VALUE(jsonDoc,''$.payment_type'') payment_type,\n       JSON_VALUE(jsonDoc,''$.payment_type_desc'') payment_type_desc  \nFROM OPENROWSET(\n    BULK ''payment_type.json'',\n    DATA_SOURCE = ''nyc_taxi_data_raw'',\n    FORMAT = ''CSV'',\n    PARSER_VERSION = ''1.0'',\n    FIELDTERMINATOR =''0x0b'',\n    FIELDQUOTE=''0x0b'',\n    ROWTERMINATOR = ''0x0a''\n ) \n WITH (\n    jsonDoc NVARCHAR(MAX)  \n ) AS payment_type'\n\n\n --change data type\n \n SELECT CAST(JSON_VALUE(jsonDoc,'$.payment_type') AS SMALLINT) payment_type,\n       CAST(JSON_VALUE(jsonDoc,'$.payment_type_desc') AS VARCHAR(15)) payment_type_desc  \nFROM OPENROWSET(\n    BULK 'payment_type.json',\n    DATA_SOURCE = 'nyc_taxi_data_raw',\n    FORMAT = 'CSV',\n    PARSER_VERSION = '1.0',\n    FIELDTERMINATOR ='0x0b',\n    FIELDQUOTE='0x0b',\n    ROWTERMINATOR = '0x0a'\n ) \n WITH (\n    jsonDoc NVARCHAR(MAX)\n ) AS payment_type\n\n--Here data type is changed to smallint, varchar\nEXEC sp_describe_first_result_set N'\nSELECT CAST(JSON_VALUE(jsonDoc,''$.payment_type'') AS SMALLINT) payment_type,\n       CAST(JSON_VALUE(jsonDoc,''$.payment_type_desc'') AS VARCHAR(15)) payment_type_desc  \nFROM OPENROWSET(\n    BULK ''payment_type.json'',\n    DATA_SOURCE = ''nyc_taxi_data_raw'',\n    FORMAT = ''CSV'',\n    PARSER_VERSION = ''1.0'',\n    FIELDTERMINATOR =''0x0b'',\n    FIELDQUOTE=''0x0b'',\n    ROWTERMINATOR = ''0x0a''\n ) \n WITH (\n    jsonDoc NVARCHAR(MAX)  \n ) AS payment_type'\n\n",
			"metadata": {
				"language": "sql"
			},
			"currentConnection": {
				"databaseName": "nyc_taxi_discovery",
				"poolName": "Built-in"
			},
			"resultLimit": 5000
		},
		"type": "SqlQuery"
	}
}